{"PriorRequest":{"Header":{"SenderID":"6811","ReceiverID":"TPA002","TransactionDate":"30/03/2024 12:58","RecordCount":"1","DispositionFlag":"PRODUCTION","PayerID":"INS017"},"Authorization":{"Type":"Authorization","ID":"6811--2700-20240329174809","RequestType":"New","RequestReferenceNumber":"","MemberID":"2B47-A413-8C46-DBC2","Weight":"1.0","EmiratesIDNumber":"784-1986-2171515-4","DateOrdered":"30/03/2024 12:58","DateOfBirth":"25/07/1986","Gender":"Male","Encounter":{"FacilityID":"6811","Type":"1"},"Diagnosis":[{"Type":"Principal","Code":"K04.7","DxInfo":null}],"Activity":[{"ID":"1784","ActivityReference":"","Start":"29/03/2024 12:58","Type":"6","Code":"D0230","Location":"2","Quantity":"1","Unit":"1","Net":"36.00","Clinician":"D74431","Duration":"1","Observation":[{"Type":"UniversalDental","Code":"UniversalNumberingSystemDental","Value":"4","ValueType":"ToothNumber"}]},{"ID":"1783","ActivityReference":"","Start":"29/03/2024 12:58","Type":"6","Code":"D0230","Location":"2","Quantity":"1","Unit":"1","Net":"36.00","Clinician":"D74431","Duration":"1","Observation":[{"Type":"UniversalDental","Code":"UniversalNumberingSystemDental","Value":"13","ValueType":"ToothNumber"}]},{"ID":"1782","ActivityReference":"","Start":"29/03/2024 12:58","Type":"6","Code":"D0220","Location":"2","Quantity":"1","Unit":"1","Net":"36.00","Clinician":"D74431","Duration":"1","Observation":[{"Type":"UniversalDental","Code":"UniversalNumberingSystemDental","Value":"21","ValueType":"ToothNumber"}]},{"ID":"1781","ActivityReference":"","Start":"29/03/2024 12:58","Type":"6","Code":"D0120","Location":"2","Quantity":"1","Unit":"1","Net":"64.80","Clinician":"D74431","Duration":"1","Observation":[{"Type":"UniversalDental","Code":"UniversalNumberingSystemDental","Value":"21","ValueType":"ToothNumber"}]}]}}}