{"PriorRequest":{"Header":{"SenderID":"DHA-F-0045618","ReceiverID":"5654","TransactionDate":"07/03/2024 11:14","RecordCount":"1","DispositionFlag":"TEST","PayerID":"TPA5436"},"Authorization":{"Type":"Authorization","ID":"DHA-F-123456--665-20240218170747","RequestType":"New","RequestReferenceNumber":"","MemberID":"INSSUKADNIC9876543210","Weight":"1.0","EmiratesIDNumber":"784-1991-4489987-2","DateOrdered":"07/03/2024 11:14","DateOfBirth":"01/01/1990","Gender":"Female","Encounter":{"FacilityID":"DHA-F-0045618","Type":"1"},"Diagnosis":[{"Type":"Principal","Code":"M02.069","DxInfo":null}],"Activity":[{"ID":"183","ActivityReference":"","Start":"18/02/2024 11:14","Type":"5","Code":"ADNIC-07","Location":"2","Quantity":"1","Unit":"1","Net":"191.25","Clinician":"GD10001","Duration":"1","Observation":null},{"ID":"181","ActivityReference":"","Start":"18/02/2024 11:14","Type":"9","Code":"ADNIC-RADIOLOGY","Location":"2","Quantity":"1","Unit":"1","Net":"356.25","Clinician":"GD10001","Duration":"1","Observation":null}]}}}